wykop/__init__.py
wykop/wykop_api.py
wykop-1.0.4.dist-info/METADATA
wykop-1.0.4.dist-info/WHEEL
wykop-1.0.4.dist-info/top_level.txt
wykop-1.0.4.dist-info/RECORD
